py_rtprio-1.3.1.dist-info/DESCRIPTION.rst
py_rtprio-1.3.1.dist-info/METADATA
py_rtprio-1.3.1.dist-info/RECORD
py_rtprio-1.3.1.dist-info/WHEEL
py_rtprio-1.3.1.dist-info/metadata.json
py_rtprio-1.3.1.dist-info/top_level.txt
rtprio/__init__.py
rtprio/rtprio.py
